repopip/.env
repopip/__init__.py
repopip/__main__.py
repopip/simple.py
repopip/site.py
repopip/util.py
repopip/local_repo/__init__.py
repopip/local_repo/configurator.py
repopip/local_repo/pipd.py
repopip/local_repo/repo.py
repopip/static/favicon.png
repopip/static/css/styles.css
repopip/static/fonts/Montserrat-Regular.ttf
repopip/static/js/script.js
repopip/templates/base.html
repopip/templates/blocks/footer.html
repopip/templates/blocks/header.html
repopip/templates/blocks/navbar.html
repopip/templates/pages/configuracion.html.j2
repopip/templates/pages/contact.html.j2
repopip/templates/pages/index.html.j2
repopip/templates/pages/packages.html.j2
repopip/templates/simple/pakage.html.j2
repopip/templates/simple/simple.html.j2
repopip/translations/__init__.py
repopip/translations/en.json
repopip/translations/es.json
repopip/translations/translator.py
repopip-0.3.1.dist-info/METADATA
repopip-0.3.1.dist-info/WHEEL
repopip-0.3.1.dist-info/top_level.txt
repopip-0.3.1.dist-info/RECORD
